nonebot_plugin_gpt_sovits-0.2.0.dist-info/METADATA
nonebot_plugin_gpt_sovits-0.2.0.dist-info/WHEEL
nonebot_plugin_gpt_sovits-0.2.0.dist-info/licenses/LICENSE
nonebot_plugin_gpt_sovits/__init__.py
nonebot_plugin_gpt_sovits/config.py
nonebot_plugin_gpt_sovits/models.py
nonebot_plugin_gpt_sovits/utils.py
nonebot_plugin_gpt_sovits-0.2.0.dist-info/RECORD
