Metadata-Version: 2.1
Name: nonebot-plugin-gpt-sovits
Version: 0.2.0
Summary: ✨ NoneBot2 Plugin for GPT-SoVITS ✨
Author-Email: zhaomaoniu <2667292003@qq.com>
License: MIT
Requires-Python: >=3.9
Requires-Dist: nonebot2>=2.3.0
Requires-Dist: nonebot-plugin-alconna>=0.52.0
Requires-Dist: aiohttp>=3.9.5
Requires-Dist: pydub>=0.25.1
